sfm_utils/__init__.py
sfm_utils/alicevision.py
sfm_utils/io.py
sfm_utils/openmvg.py
sfm_utils/sfm.py
test/__init__.py
test/sfm_utils_tests.py
PySfMUtils-1.2.0.dist-info/LICENSE
PySfMUtils-1.2.0.dist-info/METADATA
PySfMUtils-1.2.0.dist-info/WHEEL
PySfMUtils-1.2.0.dist-info/top_level.txt
PySfMUtils-1.2.0.dist-info/RECORD
