Metadata-Version: 2.1
Name: PySfMUtils
Version: 1.2.0
Summary: A Python library for interacting with Structure-from-Motion projects
Home-page: https://gitlab.com/educelab/sfm-utils
Author: Seth Parker
Author-email: c.seth.parker@uky.edu
License: UNKNOWN
Platform: UNKNOWN
Classifier: Programming Language :: Python :: 3
Classifier: License :: OSI Approved :: GNU General Public License v3 or later (GPLv3+)
Classifier: Operating System :: OS Independent
Requires-Python: >=3.6
Requires-Dist: numpy (>=1.15)
